automation_toolkit/__init__.py
automation_toolkit/core.py
automation_toolkit-0.2.5.dist-info/licenses/LICENSE
automation_toolkit-0.2.5.dist-info/METADATA
automation_toolkit-0.2.5.dist-info/WHEEL
automation_toolkit-0.2.5.dist-info/top_level.txt
automation_toolkit-0.2.5.dist-info/RECORD
